uts/__init__.py
uts/ema.py
uts/gradient.py
uts/peak_detection.py
uts/rolling.py
uts/sma.py
uts/thresholding.py
uts/zscore.py
pyUTSAlgorithms-0.1.3.dist-info/LICENSE
pyUTSAlgorithms-0.1.3.dist-info/METADATA
pyUTSAlgorithms-0.1.3.dist-info/WHEEL
pyUTSAlgorithms-0.1.3.dist-info/top_level.txt
pyUTSAlgorithms-0.1.3.dist-info/RECORD
