Metadata-Version: 2.1
Name: pyUTSAlgorithms
Version: 0.1.3
Summary: pyUTSAlgorithms (Unevenly Spaced Time Series Algorithms) Python package computes rolling statistics for uneven time series data.
Home-page: https://github.com/mariolpantunes/pyUTSAlgorithms
Author: Mário Antunes
Author-email: mario.antunes@ua.pt
Classifier: Programming Language :: Python :: 3
Classifier: License :: OSI Approved :: MIT License
Classifier: Operating System :: OS Independent
Requires-Python: >=3.8
License-File: LICENSE
Requires-Dist: numpy >=1.23
